Metadata-Version: 1.1
Name: rpisensors
Version: 0.2.1
Summary: Raspberry Pi Sensors
Home-page: https://github.com/altosz/rpisensors
Author: Alexei Tishin
Author-email: altos.z@gmail.com
License: GPLv2
Platform: UNKNOWN
Classifier: Development Status :: 4 - Beta
Classifier: Intended Audience :: Developers
Classifier: Operating System :: POSIX :: Linux
Classifier: Programming Language :: Python :: 2.6
Classifier: Programming Language :: Python :: 2.7
Classifier: License :: OSI Approved :: GNU General Public License v2 (GPLv2)
Classifier: Topic :: System :: Hardware
Classifier: Topic :: Software Development :: Embedded Systems
